README.md
ftpsync.1
setup.py
bin/ftpsync
ftpsync/__init__.py
ftpsync.egg-info/PKG-INFO
ftpsync.egg-info/SOURCES.txt
ftpsync.egg-info/dependency_links.txt
ftpsync.egg-info/top_level.txt