Metadata-Version: 1.1
Name: ftpsync
Version: 1.2.1
Summary: Sync local path with FTP remote efficiently by transmitting only what is necessary
Home-page: http://github.com/lpenz/ftpsync
Author: Leandro Lisboa Penz
Author-email: lpenz@lpenz.org
License: GPL2
Platform: UNKNOWN
Classifier: Development Status :: 5 - Production/Stable
Classifier: Environment :: Console
Classifier: License :: OSI Approved :: GNU General Public License v2 or later (GPLv2+)
Classifier: Operating System :: OS Independent
Classifier: Programming Language :: Python
Classifier: Programming Language :: Python :: 3
